cli.py
liewa/__init__.py
liewa/liewa_cli/__init__.py
liewa/liewa_cli/apod.py
liewa/liewa_cli/full_disks.py
liewa/liewa_cli/image_parser.py
liewa/liewa_cli/main.py
liewa/liewa_cli/nasa_sdo.py
liewa/liewa_cli/sentinel.py
liewa/liewa_cli/set_background.py
liewa/liewa_cli/utils.py
liewa/liewa_cli/recources/config1.yml
liewa/liewa_cli/recources/config2.yml
liewa/liewa_cli/recources/config3.yml
liewa/liewa_cli/recources/config4.yml
liewa/liewa_cli/recources/gui_config.yml
liewa/liewa_gui/__init__.py
liewa/liewa_gui/designer_main.py
liewa/liewa_gui/designer_planet.py
liewa/liewa_gui/icon.svg
liewa/liewa_gui/main.py
liewa/liewa_gui/planet_dialog.py
liewa/liewa_gui/scheduler.py
liewa-3.4.4.data/scripts/liewa-cli
liewa-3.4.4.data/scripts/liewa-gui
liewa-3.4.4.dist-info/licenses/LICENSE
liewa-3.4.4.dist-info/METADATA
liewa-3.4.4.dist-info/WHEEL
liewa-3.4.4.dist-info/top_level.txt
liewa-3.4.4.dist-info/RECORD
