Metadata-Version: 2.4
Name: liewa
Version: 3.4.4
Summary: Generate synthetic background images with near real time satellite images.
Home-page: https://github.com/lennart-rth/Live-Earth-Wallpapers
Author: lennart-rth
License: GNU
Keywords: Desktop Backgroundimage Satellite Live Earth meteosat himawari goes Space Images
Classifier: Programming Language :: Python :: 3
Classifier: License :: OSI Approved :: GNU General Public License v3 (GPLv3)
Classifier: Operating System :: OS Independent
License-File: LICENSE
Requires-Dist: beautifulsoup4
Requires-Dist: Pillow
Requires-Dist: numpy
Requires-Dist: opencv_python
Requires-Dist: PyYAML
Requires-Dist: requests
Requires-Dist: PyQt5
Dynamic: author
Dynamic: classifier
Dynamic: description
Dynamic: description-content-type
Dynamic: home-page
Dynamic: keywords
Dynamic: license
Dynamic: license-file
Dynamic: requires-dist
Dynamic: summary
